{
	"schemaVersion": 1,
	"id": "wm",
	"version": "${version}",
	"name": "wm",
	"description": "This is an example description! Tell everyone what your mod is about!",
	"authors": [
		"Me!"
	],
	"contact": {
		"homepage": "https://fabricmc.net/",
		"sources": "https://github.com/FabricMC/fabric-example-mod"
	},
	"license": "CC0-1.0",
	"icon": "assets/wm/icon.png",
	"environment": "*",
	"entrypoints": {
		"main": [
			"wm.modid.Wm"
		],
		"client": [
			"wm.modid.client.WmClient"
		]
	},
	"mixins": [
		"wm.mixins.json",
		{
			"config": "wm.client.mixins.json",
			"environment": "client"
		}
	],
	"depends": {
		"fabricloader": ">=0.19.2",
		"minecraft": "~26.1.2",
		"java": ">=25",
		"fabric-api": "*"
	}
}